MANIFEST.in
README.md
setup.py
wanikani/__init__.py
wanikani/cli.py
wanikani/core.py
wanikani/django.py
wanikani.egg-info/PKG-INFO
wanikani.egg-info/SOURCES.txt
wanikani.egg-info/dependency_links.txt
wanikani.egg-info/entry_points.txt
wanikani.egg-info/requires.txt
wanikani.egg-info/top_level.txt