Metadata-Version: 1.1
Name: wanikani
Version: 0.1
Summary: Python Library for WaniKani
Home-page: http://github.com/kfdm/wanikani/
Author: Paul Traylor
Author-email: UNKNOWN
License: UNKNOWN
Platform: UNKNOWN
Classifier: Development Status :: 3 - Alpha
Classifier: Intended Audience :: Developers
Classifier: License :: OSI Approved :: MIT License
Classifier: Natural Language :: English
Classifier: Operating System :: OS Independent
Classifier: Programming Language :: Python :: 2.7
